<?xml version="1.0" encoding="utf-8" ?><dwsync><file name="avante-basins.jpeg" server="ftp.corianuk.com" local="3466827944" remote="16351731108" /><file name="cascada-shower-tray.jpg" server="ftp.corianuk.com" local="3466828742" remote="16351731108" /><file name="corian-edging-strips.jpg" server="ftp.corianuk.com" local="3466828761" remote="16351731108" /><file name="corian-mixa-sinks.jpg" server="ftp.corianuk.com" local="3466828751" remote="16351731108" /><file name="corian-sheets.jpg" server="ftp.corianuk.com" local="3466828679" remote="16351731108" /><file name="corian-sinks.jpg" server="ftp.corianuk.com" local="3466828723" remote="16351731108" /><file name="corian-vanity-basins.jpg" server="ftp.corianuk.com" local="3466828716" remote="16351731108" /><file name="custom-made-basins healcare-bowls.jpeg" server="ftp.corianuk.com" local="3466828784" remote="16351731108" /><file name="fontana-corian-vanity-basins-baby-baths.jpg" server="ftp.corianuk.com" local="3466828733" remote="16351731108" /><file name="fontana-sink-stainless-base.jpg" server="ftp.corianuk.com" local="3466828699" remote="16351731108" /><file name="hettich-hinge.jpg" server="ftp.corianuk.com" local="3466828774" remote="16351731108" /><file name="led-tape-reels.jpg" server="ftp.corianuk.com" local="3466828768" remote="16351731108" /><file name="avante-basins.jpeg" server="217.199.187.250" local="3466827944" remote="16352160948" /><file name="cascada-shower-tray.jpg" server="217.199.187.250" local="3466828742" remote="16352160948" /><file name="corian-edging-strips.jpg" server="217.199.187.250" local="3466828761" remote="16352160948" /><file name="corian-mixa-sinks.jpg" server="217.199.187.250" local="3466828751" remote="16352160948" /><file name="corian-sheets.jpg" server="217.199.187.250" local="3466828679" remote="16352160948" /><file name="corian-sinks.jpg" server="217.199.187.250" local="3466828723" remote="16352160948" /><file name="corian-vanity-basins.jpg" server="217.199.187.250" local="3466828716" remote="16352160948" /><file name="custom-made-basins healcare-bowls.jpeg" server="217.199.187.250" local="3466828784" remote="16352160948" /><file name="fontana-corian-vanity-basins-baby-baths.jpg" server="217.199.187.250" local="3466828733" remote="16352160948" /><file name="fontana-sink-stainless-base.jpg" server="217.199.187.250" local="3466828699" remote="16352160948" /><file name="hettich-hinge.jpg" server="217.199.187.250" local="3466828774" remote="16352160948" /><file name="led-tape-reels.jpg" server="217.199.187.250" local="3466828768" remote="16352161008" /></dwsync>